
[
    {
        "groupCode": "904522236806062080", 
        "shareCode": "8E544CDD476CD86C80C209F59E570461", 
        "sumBeanNumStr": "0", 
        "activityId": 156, 
        "userName": "D15828193643"
    }, 
    {
        "groupCode": "904522251117158400", 
        "shareCode": "6F0BA54025DF3717A59FAEE03A268296", 
        "sumBeanNumStr": "0", 
        "activityId": 156, 
        "userName": "ChristinaYimi"
    }, 
    {
        "groupCode": "904522274814976000", 
        "shareCode": "3EAE3E0170A382369E06F0DF6B75BDF6AD1DAAB9A3E3F6CBAFDE81EEB7393333", 
        "sumBeanNumStr": "0", 
        "activityId": 156, 
        "userName": "jd_54d81dc6e39cd"
    }, 
    {
        "groupCode": "904522298877566976", 
        "shareCode": "622CBC671646A1E114974B35B00A2AF0", 
        "sumBeanNumStr": "0", 
        "activityId": 156, 
        "userName": "691018079_m"
    }, 
    {
        "groupCode": "904522327798210560", 
        "shareCode": "6D77A0F38C9B18205D436BDF6E0466C3", 
        "sumBeanNumStr": "0", 
        "activityId": 156, 
        "userName": "-夜夜夜夜-"
    }, 
    {
        "groupCode": "904522327798210560", 
        "shareCode": "6D77A0F38C9B18205D436BDF6E0466C3", 
        "sumBeanNumStr": "0", 
        "activityId": 156, 
        "userName": "-夜夜夜夜-"
    }, 
    {
        "groupCode": "904523174955212800", 
        "shareCode": "2B2B4944BC7F3CB3325605A27FA2993B", 
        "sumBeanNumStr": "0", 
        "activityId": 156, 
        "userName": "w654781787"
    }, 
    {
        "groupCode": "904523209355976704", 
        "shareCode": "39DDE92EAAF3C7FE3EC7CEF230457213AD1DAAB9A3E3F6CBAFDE81EEB7393333", 
        "sumBeanNumStr": "0", 
        "activityId": 156, 
        "userName": "jd_5e749a72802a9"
    }
]
